Metadata-Version: 1.1
Name: EHNconverter
Version: 1.0.0
Summary: EHN 410 converter.
Home-page: UNKNOWN
Author: Hanro van der Westhuizen
Author-email: u18141235@tuks.co.za
License: MIT
Keywords: EHN
Platform: UNKNOWN
Classifier: Development Status :: 5 - Production/Stable
Classifier: Intended Audience :: Education
Classifier: Operating System :: Microsoft :: Windows :: Windows 10
Classifier: License :: OSI Approved :: MIT License
Classifier: Programming Language :: Python :: 3
